verisocks/__init__.py
verisocks/utils.py
verisocks/verisocks.py
verisocks/cli/__init__.py
verisocks/cli/wizard.py
verisocks-1.4.0.dist-info/METADATA
verisocks-1.4.0.dist-info/WHEEL
verisocks-1.4.0.dist-info/entry_points.txt
verisocks-1.4.0.dist-info/top_level.txt
verisocks-1.4.0.dist-info/RECORD
