Metadata-Version: 2.4
Name: verisocks
Version: 1.4.0
Summary: Python client to communicate with Verisocks server.
Home-page: https://github.com/jchabloz/verisocks
Author: jchabloz
License: MIT
Requires-Dist: enum34; python_version < "3.4"
Requires-Dist: Mako>=1.0.0
Requires-Dist: PyYAML>=5.0.0
